{
    "routeNumber": "25A",
    "origin": "Saibaba Kovil",
    "destination": "Perur",
    "stops": [
        {
            "stop_name": "Saibaba Kovil"
        },
        {
            "stop_name": "Murugan mills - MTP rd"
        },
        {
            "stop_name": "Muthu theatre - MTP rd"
        },
        {
            "stop_name": "TVS - MTP rd"
        },
        {
            "stop_name": "North Coimbatore/Vadakovai"
        },
        {
            "stop_name": "Flower Market"
        },
        {
            "stop_name": "Sukravarpettai"
        },
        {
            "stop_name": "Marakkadai"
        },
        {
            "stop_name": "Town Hall"
        },
        {
            "stop_name": "Karuppagoundan st"
        },
        {
            "stop_name": "Chetti veedhi - Perur rd"
        },
        {
            "stop_name": "Shivalaya - Perur rd"
        },
        {
            "stop_name": "Muthusamy Colony - Selvapuram"
        },
        {
            "stop_name": "LIC Colony - Selvapuram"
        },
        {
            "stop_name": "Telungupalayam Pirivu - Perur"
        },
        {
            "stop_name": "Aathupalam - Perur rd"
        },
        {
            "stop_name": "Tamil kalloori - Perur"
        },
        {
            "stop_name": "Perur"
        }
    ]
}